MANIFEST.in
README.rst
setup.cfg
setup.py
tests/__init__.py
tests/base.py
tests/test_auth_controller.py
tests/test_controller.py
tests/test_partials.py
tests/test_subblog_controller.py
tests/controllers/__init__.py
tests/controllers/root.py
tests/templates/__init__.py
tgapp_turbopress.egg-info/PKG-INFO
tgapp_turbopress.egg-info/SOURCES.txt
tgapp_turbopress.egg-info/dependency_links.txt
tgapp_turbopress.egg-info/entry_points.txt
tgapp_turbopress.egg-info/not-zip-safe
tgapp_turbopress.egg-info/requires.txt
tgapp_turbopress.egg-info/top_level.txt
turbopress/__init__.py
turbopress/bootstrap.py
turbopress/helpers.py
turbopress/partials.py
turbopress/controllers/__init__.py
turbopress/controllers/root.py
turbopress/lib/__init__.py
turbopress/lib/dal.py
turbopress/lib/forms.py
turbopress/lib/validators.py
turbopress/lib/webassets.py
turbopress/model/__init__.py
turbopress/model/ming/__init__.py
turbopress/model/ming/models.py
turbopress/model/sqla/__init__.py
turbopress/model/sqla/models.py
turbopress/public/__init__.py
turbopress/public/__init__.pyc
turbopress/public/buttons/delete.png
turbopress/public/buttons/edit.png
turbopress/public/buttons/hide.png
turbopress/public/buttons/publish.png
turbopress/public/buttons/rmattachment.png
turbopress/public/ckeditor/ckeditor.js
turbopress/public/ckeditor/config.js
turbopress/public/ckeditor/contents.css
turbopress/public/ckeditor/images/spacer.gif
turbopress/public/ckeditor/lang/_languages.js
turbopress/public/ckeditor/lang/_translationstatus.txt
turbopress/public/ckeditor/lang/af.js
turbopress/public/ckeditor/lang/ar.js
turbopress/public/ckeditor/lang/bg.js
turbopress/public/ckeditor/lang/bn.js
turbopress/public/ckeditor/lang/bs.js
turbopress/public/ckeditor/lang/ca.js
turbopress/public/ckeditor/lang/cs.js
turbopress/public/ckeditor/lang/cy.js
turbopress/public/ckeditor/lang/da.js
turbopress/public/ckeditor/lang/de.js
turbopress/public/ckeditor/lang/el.js
turbopress/public/ckeditor/lang/en-au.js
turbopress/public/ckeditor/lang/en-ca.js
turbopress/public/ckeditor/lang/en-gb.js
turbopress/public/ckeditor/lang/en.js
turbopress/public/ckeditor/lang/eo.js
turbopress/public/ckeditor/lang/es.js
turbopress/public/ckeditor/lang/et.js
turbopress/public/ckeditor/lang/eu.js
turbopress/public/ckeditor/lang/fa.js
