Metadata-Version: 1.0
Name: tgapp-turbopress
Version: 0.0.5
Summary: Pluggable Blog for TurboGears2 supporting SQLAlchemy and MongoDB
Home-page: http://bitbucket.org/axant/tgapp-turbopress
Author: AXANT
Author-email: tech@axant.it
License: UNKNOWN
Keywords: turbogears2.application
Platform: UNKNOWN
